{
    "pascom": "error",
    "jovemPan": "https://www.youtube.com/embed/yFco4RyYvNM?autoplay=1",
    "ucrania": "https://www.youtube.com/embed/eMXQwhy5ALI?autoplay=1",
    "sbt": "https://www.youtube.com/embed/0aQU4gEUZ2I?autoplay=1",
    "euroNews": "https://www.youtube.com/embed/fLtn2L7OdeI?autoplay=1",
    "franceEnglish": "https://www.youtube.com/embed/h3MuIUNCCzI?autoplay=1",
    "cnn": "https://www.youtube.com/embed/Ka_LmfxcAak?autoplay=1",
    "ritTv": "error",
    "picaPau": "error",
    "cartoonNetwork": "error",
    "recordNews": "https://www.youtube.com/embed/NyarGtVeZLM?autoplay=1",
    "ge": "https://www.youtube.com/embed/jWgZ18iA830?autoplay=1",
    "wbKids": "https://www.youtube.com/embed/ClsWWQ1lZr0?autoplay=1",
    "tvJustica": "https://www.youtube.com/embed/kGN-qZuKfas?autoplay=1",
    "nasa2": "https://www.youtube.com/embed/VFnE1bCQEyY?autoplay=1",
    "aviationTv": "https://www.youtube.com/embed/tc7jwekwN9w?autoplay=1",
    "tvCritica": "https://www.youtube.com/embed/DB3G24HcDWs?autoplay=1",
    "redeBrasil": "https://www.youtube.com/embed/D5l98-iy1XQ?autoplay=1",
    "exploreAfrica": "https://www.youtube.com/embed/QkWGGhtTA4k?autoplay=1",
    "rdcTv": "https://www.youtube.com/embed/Ooj5J-Ipwvo?autoplay=1",
    "tvAparecida": "https://www.youtube.com/embed/1KIucmaYkmU?autoplay=1",
    "aeroGuarulhos": "https://www.youtube.com/embed/3VgN8NEr9yU?autoplay=1",
    "cbn": "https://www.youtube.com/embed/jnpEmRrnlWM?autoplay=1",
    "serraRioDoRastro": "https://www.youtube.com/embed/JXO-eTMqS0Y?autoplay=1",
    "tupi": "https://www.youtube.com/embed/GoYHFXLuYbI?autoplay=1",
    "nasa": "https://www.youtube.com/embed/HlLlU_Hn-YE?autoplay=1",
    "tvSenado": "https://www.youtube.com/embed/SKuAELxcFn0?autoplay=1",
    "praiaCamboriu": "https://www.youtube.com/embed/T_M8WrRUKLM?autoplay=1",
    "novoTempo": "https://www.youtube.com/embed/2ZFgKRfN0IY?autoplay=1",
    "redeVida": "https://www.youtube.com/embed/HbaRJ5jBkJ8?autoplay=1",
    "radioCantu": "https://stm01.virtualcast.com.br:8874/live",
    "cancaoNova": "https://www.youtube.com/embed/LRHUiB6VVKM?autoplay=1"
}